dotenvy_py/__init__.py
dotenvy_py-0.1.0.dist-info/licenses/LICENSE
tests/__init__.py
tests/test_dotenvy.py
dotenvy_py-0.1.0.dist-info/METADATA
dotenvy_py-0.1.0.dist-info/WHEEL
dotenvy_py-0.1.0.dist-info/top_level.txt
dotenvy_py-0.1.0.dist-info/RECORD
