Metadata-Version: 2.4
Name: dotenvy-py
Version: 0.1.0
Summary: A Python port of Rust's dotenvy with first-occurrence-wins behavior
Home-page: https://github.com/neutroboxing/dotenvy-py
Author: NeutrobeatBoxing
Author-email: dev@neutroboxing.com
Keywords: dotenv,environment,config,env,dotenvy,rust
Classifier: Programming Language :: Python :: 3
Classifier: Programming Language :: Python :: 3.7
Classifier: Programming Language :: Python :: 3.8
Classifier: Programming Language :: Python :: 3.9
Classifier: Programming Language :: Python :: 3.10
Classifier: Programming Language :: Python :: 3.11
Classifier: License :: OSI Approved :: MIT License
Classifier: Operating System :: OS Independent
Classifier: Development Status :: 4 - Beta
Classifier: Intended Audience :: Developers
Classifier: Topic :: Software Development :: Libraries :: Python Modules
Requires-Python: >=3.7
License-File: LICENSE
Dynamic: author
Dynamic: author-email
Dynamic: classifier
Dynamic: description
Dynamic: description-content-type
Dynamic: home-page
Dynamic: keywords
Dynamic: license-file
Dynamic: requires-python
Dynamic: summary
